pymento_meg/__init__.py
pymento_meg/cli.py
pymento_meg/config.py
pymento_meg/pymento.py
pymento_meg/utils.py
pymento_meg/version.py
pymento_meg/orig/__init__.py
pymento_meg/orig/behavior.py
pymento_meg/orig/restructure.py
pymento_meg/proc/__init__.py
pymento_meg/proc/artifacts.py
pymento_meg/proc/behavior.py
pymento_meg/proc/bids.py
pymento_meg/proc/epoch.py
pymento_meg/proc/preprocess.py
pymento_meg/viz/__init__.py
pymento_meg/viz/plots.py
pymento_meg-0.1.dist-info/AUTHORS.rst
pymento_meg-0.1.dist-info/LICENSE
pymento_meg-0.1.dist-info/METADATA
pymento_meg-0.1.dist-info/WHEEL
pymento_meg-0.1.dist-info/entry_points.txt
pymento_meg-0.1.dist-info/top_level.txt
pymento_meg-0.1.dist-info/RECORD
