Metadata-Version: 2.1
Name: pymento-meg
Version: 0.1
Summary: A Python package to analyze Memento MEG data
Home-page: https://github.com/adswa/pymento
Author: Adina Wagner
Author-email: adina.wagner@t-online.de
License: MIT license
Keywords: pymento
Platform: UNKNOWN
Classifier: Development Status :: 2 - Pre-Alpha
Classifier: Intended Audience :: Developers
Classifier: License :: OSI Approved :: MIT License
Classifier: Natural Language :: English
Classifier: Programming Language :: Python :: 3
Classifier: Programming Language :: Python :: 3.7
Classifier: Programming Language :: Python :: 3.8
Requires-Python: >=3.7
Requires-Dist: matplotlib
Requires-Dist: mne
Requires-Dist: mne-bids
